SpringCloudFinchleySr2ZhongwenWendang/README.md
SpringCloudFinchleySr2ZhongwenWendang/__init__.py
SpringCloudFinchleySr2ZhongwenWendang/__main__.py
SpringCloudFinchleySr2ZhongwenWendang/file.epub
SpringCloudFinchleySr2ZhongwenWendang/index.html
SpringCloudFinchleySr2ZhongwenWendang/css/__init__.py
SpringCloudFinchleySr2ZhongwenWendang/css/annotations.css
SpringCloudFinchleySr2ZhongwenWendang/css/main.css
SpringCloudFinchleySr2ZhongwenWendang/css/normalize.css
SpringCloudFinchleySr2ZhongwenWendang/css/popup.css
SpringCloudFinchleySr2ZhongwenWendang/font/__init__.py
SpringCloudFinchleySr2ZhongwenWendang/font/fontello.eot
SpringCloudFinchleySr2ZhongwenWendang/font/fontello.svg
SpringCloudFinchleySr2ZhongwenWendang/font/fontello.ttf
SpringCloudFinchleySr2ZhongwenWendang/font/fontello.woff
SpringCloudFinchleySr2ZhongwenWendang/img/__init__.py
SpringCloudFinchleySr2ZhongwenWendang/img/annotator-glyph-sprite.png
SpringCloudFinchleySr2ZhongwenWendang/img/annotator-icon-sprite.png
SpringCloudFinchleySr2ZhongwenWendang/img/apple-touch-icon.png
SpringCloudFinchleySr2ZhongwenWendang/img/cancelfullscreen.png
SpringCloudFinchleySr2ZhongwenWendang/img/close.png
SpringCloudFinchleySr2ZhongwenWendang/img/fullscreen.png
SpringCloudFinchleySr2ZhongwenWendang/img/loader.gif
SpringCloudFinchleySr2ZhongwenWendang/img/menu-icon.png
SpringCloudFinchleySr2ZhongwenWendang/img/save.png
SpringCloudFinchleySr2ZhongwenWendang/img/saved.png
SpringCloudFinchleySr2ZhongwenWendang/img/settings-s.png
SpringCloudFinchleySr2ZhongwenWendang/img/settings.png
SpringCloudFinchleySr2ZhongwenWendang/img/star.png
SpringCloudFinchleySr2ZhongwenWendang/js/__init__.py
SpringCloudFinchleySr2ZhongwenWendang/js/epub.js
SpringCloudFinchleySr2ZhongwenWendang/js/epub.min.js
SpringCloudFinchleySr2ZhongwenWendang/js/epub.min.map
SpringCloudFinchleySr2ZhongwenWendang/js/hooks.min.js
SpringCloudFinchleySr2ZhongwenWendang/js/hooks.min.map
SpringCloudFinchleySr2ZhongwenWendang/js/reader.js
spring_cloud_finchley_sr2_zhongwen_wendang-2024.3.5.0.dist-info/METADATA
spring_cloud_finchley_sr2_zhongwen_wendang-2024.3.5.0.dist-info/WHEEL
spring_cloud_finchley_sr2_zhongwen_wendang-2024.3.5.0.dist-info/entry_points.txt
spring_cloud_finchley_sr2_zhongwen_wendang-2024.3.5.0.dist-info/top_level.txt
spring_cloud_finchley_sr2_zhongwen_wendang-2024.3.5.0.dist-info/RECORD
